storagetools/__init__.py
storagetools/context.py
storagetools/database.py
storagetools/db_interface.py
storagetools/helpers.py
storagetools/ml.py
storagetools/model.py
storagetools/sql_scripts/database_lookup_view.sql
storagetools/sql_scripts/database_schema.sql
ts_storagetools-0.2.2.dist-info/licenses/LICENSE
ts_storagetools-0.2.2.dist-info/METADATA
ts_storagetools-0.2.2.dist-info/WHEEL
ts_storagetools-0.2.2.dist-info/top_level.txt
ts_storagetools-0.2.2.dist-info/RECORD
