Metadata-Version: 2.4
Name: ts-storagetools
Version: 0.2.2
Summary: SQLite schema, Python classes and data management tools for working with time series from engineering test beds
Author-email: Mauritz Mälzer <mauritz.maelzer@tu-dresden.de>
Project-URL: Homepage, https://codeberg.org/mlzr/storagetools
Classifier: License :: OSI Approved :: BSD License
Classifier: Programming Language :: Python :: 3
Classifier: Operating System :: OS Independent
Requires-Python: >=3.13
License-File: LICENSE
Requires-Dist: tqdm
Requires-Dist: rich
Requires-Dist: toolz
Requires-Dist: lmdb>=1.6.2
Requires-Dist: typeguard>=4.4.2
Dynamic: license-file
